[
  {
    "arguments": [
      "/usr/bin/g++",
      "-DHAVE_CONFIG_H",
      "-I/usr/include/c++/11",
      "-I.",
      "-I../..",
      "-DLIBDRAWIO_BUILD=1",
      "-I../../inc",
      "-I/home/george/internship/drawings/librevenge/inc",
      "-I/home/george/internship/drawings/librevenge/inc",
      "-I/usr/include/libxml2",
      "-DDEBUG",
      "-g",
      "-g",
      "-O2",
      "-fvisibility=hidden",
      "-DLIBDRAWIO_VISIBILITY",
      "-Wall",
      "-Wextra",
      "-pedantic",
      "-Wshadow",
      "-Wunused-variable",
      "-Weffc++",
      "-O0",
      "-c",
      "-fPIC",
      "-DPIC",
      "-o",
      ".libs/DRAWIODocument.o",
      "DRAWIODocument.cpp"
    ],
    "directory": "/home/george/internship/drawings/libdrawio/src/lib",
    "file": "/home/george/internship/drawings/libdrawio/src/lib/DRAWIODocument.cpp",
    "output": "/home/george/internship/drawings/libdrawio/src/lib/.libs/DRAWIODocument.o"
  },
  {
    "arguments": [
      "/usr/bin/g++",
      "-DHAVE_CONFIG_H",
      "-I/usr/include/c++/11",
      "-I.",
      "-I../..",
      "-DLIBDRAWIO_BUILD=1",
      "-I../../inc",
      "-I/home/george/internship/drawings/librevenge/inc",
      "-I/home/george/internship/drawings/librevenge/inc",
      "-I/usr/include/libxml2",
      "-DDEBUG",
      "-g",
      "-g",
      "-O2",
      "-fvisibility=hidden",
      "-DLIBDRAWIO_VISIBILITY",
      "-Wall",
      "-Wextra",
      "-pedantic",
      "-Wshadow",
      "-Wunused-variable",
      "-Weffc++",
      "-O0",
      "-c",
      "-fPIC",
      "-DPIC",
      "-o",
      ".libs/libdrawio_utils.o",
      "libdrawio_utils.cpp"
    ],
    "directory": "/home/george/internship/drawings/libdrawio/src/lib",
    "file": "/home/george/internship/drawings/libdrawio/src/lib/libdrawio_utils.cpp",
    "output": "/home/george/internship/drawings/libdrawio/src/lib/.libs/libdrawio_utils.o"
  }
]
